CHANGES.rst
LICENSE.txt
MANIFEST.in
README.rst
setup.py
update_cpp.sh
crfsuite/.git
crfsuite/.gitignore
crfsuite/.travis.yml
crfsuite/AUTHORS
crfsuite/COPYING
crfsuite/ChangeLog
crfsuite/INSTALL
crfsuite/Makefile.am
crfsuite/README.md
crfsuite/autogen.sh
crfsuite/configure.ac
crfsuite/crfsuite.sln
crfsuite/genbinary.sh.in
crfsuite/tap-driver.sh
crfsuite/bench/accuracy.py
crfsuite/bench/bench.py
crfsuite/bench/bench_crfpp.py
crfsuite/bench/bench_crfsgd.py
crfsuite/bench/bench_crfsuite-0.11.py
crfsuite/bench/bench_crfsuite.py
crfsuite/bench/bench_mallet.py
crfsuite/bench/bench_wapiti.py
crfsuite/bench/collect.py
crfsuite/bench/crfsuite_to_mallet.py
crfsuite/bench/plot_performance.py
crfsuite/doc/Doxyfile
crfsuite/doc/footer.html
crfsuite/doc/header.html
crfsuite/example/chunking.py
crfsuite/example/crfutils.py
crfsuite/example/ner.py
crfsuite/example/pos.py
crfsuite/example/template.py
crfsuite/frontend/Makefile.am
crfsuite/frontend/crfsuite.1
crfsuite/frontend/dump.c
crfsuite/frontend/frontend.vcxproj
crfsuite/frontend/iwa.c
crfsuite/frontend/iwa.h
crfsuite/frontend/learn.c
crfsuite/frontend/main.c
crfsuite/frontend/option.c
crfsuite/frontend/option.h
crfsuite/frontend/readdata.h
crfsuite/frontend/reader.c
crfsuite/frontend/tag.c
crfsuite/include/Makefile.am
crfsuite/include/crfsuite.h
crfsuite/include/crfsuite.hpp
crfsuite/include/crfsuite_api.hpp
crfsuite/include/os.h
crfsuite/lib/cqdb/COPYING
crfsuite/lib/cqdb/Makefile.am
crfsuite/lib/cqdb/cqdb.vcxproj
crfsuite/lib/cqdb/makedist.sh
crfsuite/lib/cqdb/doc/doxyfile
crfsuite/lib/cqdb/doc/footer.html
crfsuite/lib/cqdb/include/cqdb.h
crfsuite/lib/cqdb/src/cqdb.c
crfsuite/lib/cqdb/src/lookup3.c
crfsuite/lib/cqdb/src/main.c
crfsuite/lib/crf/.gitignore
crfsuite/lib/crf/Makefile.am
crfsuite/lib/crf/crf.vcxproj
crfsuite/lib/crf/src/crf1d.h
crfsuite/lib/crf/src/crf1d_context.c
crfsuite/lib/crf/src/crf1d_encode.c
crfsuite/lib/crf/src/crf1d_feature.c
crfsuite/lib/crf/src/crf1d_model.c
crfsuite/lib/crf/src/crf1d_tag.c
python_crfsuite_extension.egg-info/PKG-INFO
python_crfsuite_extension.egg-info/SOURCES.txt
python_crfsuite_extension.egg-info/dependency_links.txt
python_crfsuite_extension.egg-info/not-zip-safe
python_crfsuite_extension.egg-info/top_level.txt
